<?xml version="1.0" encoding="iso-8859-1"?>
<Dps><Player name="Tom_Becker" team="ifc" value="18" games="13"/><Player name="Siberian_Asci" team="ifc" value="18" games="17"/><Player name="Julius_Heide" team="stp" value="15" games="17"/><Player name="Pedro_Gnèk" team="atm" value="15" games="17"/><Player name="Oliver_Hutton" team="ifc" value="15" games="17"/><Player name="Al_Deretano" team="ifc" value="12" games="17"/><Player name="Aristoteles" team="lac" value="12" games="17"/><Player name="Vince_Sparacc" team="dot" value="12" games="17"/><Player name="Josè_Altafini" team="fcs" value="12" games="17"/><Player name="Nicky_Fobbs" team="stp" value="9" games="3"/><Player name="Ora._Mallam." team="reg" value="9" games="13"/><Player name="Jack_Puppo" team="dot" value="9" games="15"/><Player name="Attilio_Mazzi" team="fcs" value="9" games="16"/><Player name="Jasa" team="pfc" value="9" games="17"/><Player name="Loris_Battacc" team="dot" value="9" games="17"/><Player name="Zandro_Bellin" team="dot" value="6" games="12"/><Player name="Diga" team="pfc" value="6" games="13"/><Player name="U_Warrior" team="otb" value="6" games="15"/><Player name="Gianluca_Savo" team="reg" value="6" games="16"/><Player name="Mark_Lenders" team="mab" value="6" games="16"/></Dps>