<?xml version="1.0" encoding="iso-8859-1"?>
<Performs><Player name="Marco_la_Foòr" team="atm" value="432" games="18"/><Player name="Mark_Kuntz" team="stp" value="408" games="18"/><Player name="Egeria" team="pfc" value="381" games="18"/><Player name="Antonio_J._Vi" team="lac" value="345" games="18"/><Player name="Gianluca_Mall" team="dot" value="339" games="14"/><Player name="Marat_Sacranò" team="atm" value="338" games="18"/><Player name="Troock_Le_Ciò" team="atm" value="332" games="18"/><Player name="Pippo_Cannelu" team="ifc" value="321" games="17"/><Player name="Andrea_Penco" team="fcs" value="320" games="18"/><Player name="Pikala_Int" team="otb" value="307" games="18"/><Player name="Bepi_Svergùl" team="atm" value="303" games="18"/><Player name="Benjie_Price" team="mab" value="294" games="18"/><Player name="Jasa" team="pfc" value="293" games="17"/><Player name="Pitotòn_Delle" team="atm" value="291" games="17"/><Player name="Andrea_Scopel" team="reg" value="288" games="18"/><Player name="Highlander" team="otb" value="285" games="18"/><Player name="Donato_Bilanc" team="fcs" value="279" games="16"/><Player name="Beverly" team="pfc" value="277" games="18"/><Player name="Joe_Saracines" team="otb" value="273" games="18"/><Player name="Concia_Oss" team="otb" value="270" games="17"/></Performs>